cypyler/Cypyler.py
cypyler/__init__.py
cypyler/utils.py
cypyler-0.2.0.dist-info/DESCRIPTION.rst
cypyler-0.2.0.dist-info/METADATA
cypyler-0.2.0.dist-info/RECORD
cypyler-0.2.0.dist-info/WHEEL
cypyler-0.2.0.dist-info/metadata.json
cypyler-0.2.0.dist-info/top_level.txt
