Metadata-Version: 2.0
Name: cypyler
Version: 0.2.0
Summary: A cython compiler for compiling source code in string form.
Home-page: https://github.com/gpkc/cypyler
Author: Guilherme Caminha
Author-email: gpkc@cin.ufpe.br
License: MIT license
Keywords: cypyler
Platform: UNKNOWN
Classifier: Development Status :: 4 - Beta
Classifier: Intended Audience :: Developers
Classifier: License :: OSI Approved :: MIT License
Classifier: Natural Language :: English
Classifier: Programming Language :: Python :: 3
Classifier: Programming Language :: Python :: 3.6
Requires-Dist: cython
Requires-Dist: numpy
